Hack/PC.v
/**
if (reset[t] == 1) out[t+1] = 0
	else if (load[t] == 1) out[t+1] = in
	else if (inc[t] == 1) out[t+1] = out[t] + 1 (integer add)
	else out[t+1] = out[t]
*/
//NOTE: The provided PC.out and PC.cmp do not match. I saved
//the PC.out as PC.out.orig. Comparing that to my own PC.out
//shows it's the same. So does comparing the testbunch results

`default_nettype none

module PC(
	input wire clk,
	input wire reset,
	input wire [15:0] in,
	input wire load,
	input wire inc,
	output wire [15:0] out
);	

    reg [15:0] pc = 16'hFFFF;
    always @(negedge clk) begin
        if (reset)
            pc <= 0;
        else if(load) 
            pc <= in;
        else if (inc)
            pc <= pc + 1;
        else
            pc <= pc;
    end
    assign out = pc;

endmodule

Hack/ALU.v
/**
 * The ALU (Arithmetic Logic Unit).
 * Computes one of the following functions:
 * x+y, x-y, y-x, 0, 1, -1, x, y, -x, -y, !x, !y,
 * x+1, y+1, x-1, y-1, x&y, x|y on two 16-bit inputs, 
 * according to 6 input bits denoted zx,nx,zy,ny,f,no.
 * In addition, the ALU computes two 1-bit outputs:
 * if the ALU output == 0, zr is set to 1; otherwise zr is set to 0;
 * if the ALU output < 0, ng is set to 1; otherwise ng is set to 0.
 */

// Implementation: the ALU logic manipulates the x and y inputs
// and operates on the resulting values, as follows:
// if (zx == 1) set x = 0        // 16-bit constant
// if (nx == 1) set x = !x       // bitwise not
// if (zy == 1) set y = 0        // 16-bit constant
// if (ny == 1) set y = !y       // bitwise not
// if (f == 1)  set out = x + y  // integer 2's complement addition
// if (f == 0)  set out = x & y  // bitwise and
// if (no == 1) set out = !out   // bitwise not
// if (out == 0) set zr = 1
// if (out < 0) set ng = 1

`default_nettype none
module ALU(
	input wire [15:0] x,		// input x (16 bit)
	input wire [15:0] y,		// input y (16 bit)
    input wire zx, 				// zero the x input?
    input wire nx, 				// negate the x input?
    input wire zy, 				// zero the y input?
    input wire ny, 				// negate the y input?
    input wire f,  				// compute out = x + y (if 1) or x & y (if 0)
    input wire no, 				// negate the out output?
    output wire [15:0] out, 	// 16-bit output
    output wire zr, 			// 1 if (out == 0), 0 otherwise
    output wire ng 			// 1 if (out < 0),  0 otherwise
);
    // your implementation comes here:

    wire [15:0] zxa;
    wire [15:0] xx;
    wire [15:0] zya;
    wire [15:0] yy;
    wire [15:0] fa;

    //x
    assign zxa = zx ? 0 : x;
    assign xx = nx ? ~zxa : zxa;

    //y
    assign zya = zy ? 0 : y;
    assign yy = ny ? ~zya : zya;

    //fa
    assign fa = f ? (xx + yy) : (xx & yy);

    //out
    assign out = no ? ~fa : fa;
    assign zr = out == 0 ? 1 : 0;
    assign ng = out[15]; // negative if MSB is 1

endmodule

Hack/Register.v
/**
 * 16-bit register:
 * If load[t] == 1 then out[t+1] = in[t]
 * else out does not change
 */

`default_nettype none

module Register(
	input clk,
	input [15:0] in,
	input load,
	output [15:0] out
);
    
    reg out = 0;
    always @(negedge clk) begin
        if (load)
            out <= in;
    end

endmodule

Hack/CPU.v
/**
 * The Hack CPU (Central Processing unit), consisting of an ALU,
 * two registers named A and D, and a program counter named PC.
 * The CPU is designed to fetch and execute instructions written in 
 * the Hack machine language. In particular, functions as follows:
 * Executes the inputted instruction according to the Hack machine 
 * language specification. The D and A in the language specification
 * refer to CPU-resident registers, while M refers to the external
 * memory location addressed by A, i.e. to Memory[A]. The inM input 
 * holds the value of this location. If the current instruction needs 
 * to write a value to M, the value is placed in outM, the address 
 * of the target location is placed in the addressM output, and the 
 * writeM control bit is asserted. (When writeM==0, any value may 
 * appear in outM). The outM and writeM outputs are combinational: 
 * they are affected instantaneously by the execution of the current 
 * instruction. The addressM and pc outputs are clocked: although they 
 * are affected by the execution of the current instruction, they commit 
 * to their new values only in the next time step. If reset==1 then the 
 * CPU jumps to address 0 (i.e. pc is set to 0 in next time step) rather 
 * than to the address resulting from executing the current instruction. 
 */
    
//instruction[16]:
//cccccccccccccccc
//
//A-instr
//0ccccccccccccccc 
//  instruction[15] == 0
//  c0...c14 is a memory location (or val)
//
//C-instruction:
//1xxaccccccdddjjj 
//  instruction[15] == 1
//
//acccc 'comp' instruction[6-12]
//  a: instruction[12]
//  c: instruction[6..11]
//ddd 'dest' instruction[3-5]
//  M: instruction[3]
//  D: instruction[4]
//  A: instruction[5]
//jjj 'jump' instruction[0-2]
//  table defined below


`default_nettype none
module CPU(
		input clk,
    	input [15:0] inM,         	// M value input  (M = contents of RAM[A])
    	input [15:0] instruction, 	// Instruction for execution
		input reset,           	// Signals whether to re-start the current
                         				// program (reset==1) or continue executing
                         				// the current program (reset==0).

    	output [15:0] outM,        // M value output
    	output writeM,          	// Write to M? 
    	output [15:0] addressM,    // Address in data memory (of M) to read
    	output [15:0] pc         	// address of next instruction
);
    wire loadA, loadD;
    wire [15:0] Aout, Dout, Ain;
    wire destA = instruction[5], 
         destD = instruction[4], 
         destM = instruction[3];
    wire [15:0] ALUy, ALUout;
    wire lt, eq, gt;
    wire jmp;
    
    /* A reg */
    assign loadA = ~instruction[15] | destA;
    //If A-instruction, instruction is input else, ALUout is input
    assign Ain = instruction[15] == 0 ? instruction : ALUout;
    Register RegA(.clk(clk), .in(Ain), .load(loadA), .out(Aout));
    
    /* D reg */
    assign loadD = instruction[15] & destD;
    Register RegD(.clk(clk), .in(ALUout), .load(loadD), .out(Dout));
        

    /* ALU */
    //Choose: is A or inM being fed to the ALU
    //0011111: x+1
    assign ALUy = instruction[12] ? inM : Aout;
    ALU Alu(
        .x(Dout), .y(ALUy), 
        .zx(instruction[11]), .nx(instruction[10]), .zy(instruction[9]), .ny(instruction[8]), .f(instruction[7]), .no(instruction[6]),
        .out(ALUout), .zr(eq), .ng(lt));
        
    /* MEM */
    assign addressM = Aout;
    assign outM = ALUout;
    assign writeM = instruction[15] & destM;

    /* PC */
    assign gt = ~eq & ~lt;

    //jmp if:
    //GT: instruction[0]
    //EQ: instruction[1]
    //LT: instruction[2]
    assign jmp = instruction[15] & (
        (instruction[0] & gt) | (instruction[1] & eq) | (instruction[2] & lt));

    PC Pc(.clk(clk), .in(Aout), .load(jmp), .inc(1'b1), .reset(reset), .out(pc));


endmodule

01_Hack1-minimal/CPU/CPU_tb.v
/*
 * Note from Phil:
 * I spent a lot of time tring to get my Register and PC timing
 * to work with the original test bench. The problem was that my
 * registers were NOT delaying the way they were supposed to.
 * Turns out, the problem seems to be with the simulation in
 * the testbench itself. Because the instruction was assigned
 * via a blocking assignment, the change was happening before
 * the clk was changed.
 * Changing the assignments to be non-blocking fixes this problem.
 * All the crazy things I was trying in code go away.
 * See:
 * https://stackoverflow.com/questions/11672239/why-is-my-d-flip-flop-not-waiting-for-the-positive-edge-of-the-clock
 */

`default_nettype none
module CPU_tb();

	integer file;
	reg clk=0;	
	reg [15:0] inM=0;
	reg [15:0] instruction=0;
	reg reset=0;
	wire [15:0] outM;
	wire writeM;
	wire [15:0] addressM;
	wire [15:0] pc;
	CPU CPU(
		.clk(clk),
		.inM(inM),
		.instruction(instruction),
		.reset(reset),
		.outM(outM),
		.writeM(writeM),
		.addressM(addressM),
		.pc(pc)
	);
	 
	always #1 clk = ~clk;

	task display;
    	#1 $fwrite(file, "| %16b | %16b | %16b | %1b | %16b | %1b | %16b |\n",pc,inM,instruction,reset,outM,writeM,addressM);
  	endtask
  	
  	initial begin
  		$dumpfile("CPU_tb.vcd");
  		$dumpvars(0, CPU_tb);
		file = $fopen("CPU.out","w");
    	$fwrite(file, "|       pc         |       inM        |    instruction   |rst|       outM       |wM |    addressM      |\n");
		

#2 instruction <= 16'b0011000000111001; // @12345
display();

#2 instruction <= 16'b1110110000010000; // D<=A
display();

#2 instruction <= 16'b0101101110100000; // @23456
display();

#2 instruction <= 16'b1110000111010000; // D<=A-D
display();

#2 instruction <= 16'b0000001111101000; // @1000
display();

#2 instruction <= 16'b1110001100001000; // M<=D
display();

#2 instruction <= 16'b0000001111101001; // @1001
display();

#2 instruction <= 16'b1110001110011000; // MD<=D-1
display();

#2 instruction <= 16'b0000001111101000; // @1000
display();

#2 instruction <= 16'b1111010011010000; // D<=D-M
#2 inM<=11111;
display();

#2 instruction <= 16'b0000000000001110; // @14
display();

#2 instruction <= 16'b1110001100000100; // D;jlt
display();

#2 instruction <= 16'b0000001111100111; // @999
display();

#2 instruction <= 16'b1110110111100000; // A<=A+1
display();

#2 instruction <= 16'b1110001100001000; // M<=D
display();

#2 instruction <= 16'b0000000000010101; // @21
display();

#2 instruction <= 16'b1110011111000010; // D+1;jeq
display();

#2 instruction <= 16'b0000000000000010; // @2
display();

#2 instruction <= 16'b1110000010010000; // D<=D+A
display();

#2 instruction <= 16'b0000001111101000; // @1000
display();

#2 instruction <= 16'b1110111010010000; // D<=-1
display();

#2 instruction <= 16'b1110001100000001; // D;JGT
display();

#2 instruction <= 16'b1110001100000010; // D;JEQ
display();

#2 instruction <= 16'b1110001100000011; // D;JGE
display();

#2 instruction <= 16'b1110001100000100; // D;JLT
display();

#2 instruction <= 16'b1110001100000101; // D;JNE
display();

#2 instruction <= 16'b1110001100000110; // D;JLE
display();

#2 instruction <= 16'b1110001100000111; // D;JMP
display();

#2 instruction <= 16'b1110101010010000; // D<=0
display();

#2 instruction <= 16'b1110001100000001; // D;JGT
display();

#2 instruction <= 16'b1110001100000010; // D;JEQ
display();

#2 instruction <= 16'b1110001100000011; // D;JGE
display();

#2 instruction <= 16'b1110001100000100; // D;JLT
display();

#2 instruction <= 16'b1110001100000101; // D;JNE
display();

#2 instruction <= 16'b1110001100000110; // D;JLE
display();

#2 instruction <= 16'b1110001100000111; // D;JMP
display();

#2 instruction <= 16'b1110111111010000; // D<=1
display();

#2 instruction <= 16'b1110001100000001; // D;JGT
display();

#2 instruction <= 16'b1110001100000010; // D;JEQ
display();

#2 instruction <= 16'b1110001100000011; // D;JGE
display();

#2 instruction <= 16'b1110001100000100; // D;JLT
display();

#2 instruction <= 16'b1110001100000101; // D;JNE
display();

#2 instruction <= 16'b1110001100000110; // D;JLE
display();

#2 instruction <= 16'b1110001100000111; // D;JMP
display();

#2 reset<=1;
display();

#2 instruction <= 16'b0111111111111111; // @32767
#2 reset<=0;
display();


$finish;
end
endmodule

01_Hack1-minimal/CPU/CPU_tb.vcd
$date
	Mon Jan 31 01:27:12 2022
$end
$version
	Icarus Verilog
$end
$timescale
	1ps
$end
$scope module CPU_tb $end
$var wire 1 ! writeM $end
$var wire 16 " pc [15:0] $end
$var wire 16 # outM [15:0] $end
$var wire 16 $ addressM [15:0] $end
$var reg 1 % clk $end
$var reg 16 & inM [15:0] $end
$var reg 16 ' instruction [15:0] $end
$var reg 1 ( reset $end
$var integer 32 ) file [31:0] $end
$scope module CPU $end
$var wire 16 * addressM [15:0] $end
$var wire 1 % clk $end
$var wire 1 + gt $end
$var wire 16 , inM [15:0] $end
$var wire 16 - instruction [15:0] $end
$var wire 1 . jmp $end
$var wire 1 / loadA $end
$var wire 1 0 loadD $end
$var wire 16 1 outM [15:0] $end
$var wire 1 ( reset $end
$var wire 1 ! writeM $end
$var wire 16 2 pc [15:0] $end
$var wire 1 3 lt $end
$var wire 1 4 eq $end
$var wire 1 5 destM $end
$var wire 1 6 destD $end
$var wire 1 7 destA $end
$var wire 16 8 Dout [15:0] $end
$var wire 16 9 Aout [15:0] $end
$var wire 16 : Ain [15:0] $end
$var wire 16 ; ALUy [15:0] $end
$var wire 16 < ALUout [15:0] $end
$scope module Alu $end
$var wire 1 = f $end
$var wire 1 > no $end
$var wire 1 ? nx $end
$var wire 1 @ ny $end
$var wire 16 A y [15:0] $end
$var wire 1 B zx $end
$var wire 1 C zy $end
$var wire 16 D zya [15:0] $end
$var wire 16 E zxa [15:0] $end
$var wire 1 4 zr $end
$var wire 16 F yy [15:0] $end
$var wire 16 G xx [15:0] $end
$var wire 16 H x [15:0] $end
$var wire 16 I out [15:0] $end
$var wire 1 3 ng $end
$var wire 16 J fa [15:0] $end
$upscope $end
$scope module Pc $end
$var wire 1 % clk $end
$var wire 1 K inc $end
$var wire 1 . load $end
$var wire 16 L out [15:0] $end
$var wire 1 ( reset $end
$var wire 16 M in [15:0] $end
$var reg 16 N pc [15:0] $end
$upscope $end
$scope module RegA $end
$var wire 1 % clk $end
$var wire 16 O in [15:0] $end
$var wire 1 / load $end
$var reg 16 P out [15:0] $end
$upscope $end
$scope module RegD $end
$var wire 1 % clk $end
$var wire 16 Q in [15:0] $end
$var wire 1 0 load $end
$var reg 16 R out [15:0] $end
$upscope $end
$upscope $end
$scope task display $end
$upscope $end
$upscope $end
$enddefinitions $end
#0
$dumpvars
b0 R
b0 Q
b0 P
b0 O
b0 N
b0 M
b0 L
1K
b0 J
b0 I
b0 H
b0 G
b0 F
b0 E
b0 D
0C
0B
b0 A
0@
0?
0>
0=
b0 <
b0 ;
b0 :
b0 9
b0 8
07
06
05
14
03
b0 2
b0 1
00
1/
0.
b0 -
b0 ,
0+
b0 *
b10000000000000000000000000000011 )
0(
b0 '
b0 &
0%
b0 $
b0 #
b0 "
0!
$end
#1
1%
#2
15
16
17
b11000000111001 :
b11000000111001 O
b1 "
b1 2
b1 L
b1 N
b11000000111001 '
b11000000111001 -
0%
#3
1%
#4
b11000000111001 $
b11000000111001 *
b11000000111001 9
b11000000111001 M
b11000000111001 P
b10 "
b10 2
b10 L
b10 N
0%
#5
1+
04
b11000000111001 #
b11000000111001 1
b11000000111001 <
b11000000111001 I
b11000000111001 Q
b11000000111001 J
b11000000111001 F
b11000000111001 D
0/
10
b11000000111001 ;
b11000000111001 A
b1111111111111111 G
05
07
b11000000111001 :
b11000000111001 O
1B
1?
b1110110000010000 '
b1110110000010000 -
1%
#6
b11 "
b11 2
b11 L
b11 N
b11000000111001 8
b11000000111001 H
b11000000111001 R
0%
#7
1%
#8
0+
13
b1111111111111111 #
b1111111111111111 1
b1111111111111111 <
b1111111111111111 I
b1111111111111111 Q
1/
b101101110100000 :
b101101110100000 O
00
b0 ;
b0 A
b0 G
b0 D
b1111111111111111 F
b1111111111111111 J
06
17
0?
1C
1@
1=
b100 "
b100 2
b100 L
b100 N
b101101110100000 '
b101101110100000 -
0%
#9
1%
#10
b101 "
b101 2
b101 L
b101 N
b101101110100000 $
b101101110100000 *
b101101110100000 9
b101101110100000 M
b101101110100000 P
0%
#11
b1010010001011111 F
1+
b1101010010011000 J
04
b101101110100000 D
b11000000111001 G
03
0/
10
b101101110100000 ;
b101101110100000 A
b11000000111001 E
b10101101100111 #
b10101101100111 1
b10101101100111 <
b10101101100111 I
b10101101100111 Q
16
07
b10101101100111 :
b10101101100111 O
0B
0C
1>
b1110000111010000 '
b1110000111010000 -
1%
#12
b11000000111001 :
b11000000111001 O
b11000000111001 #
b11000000111001 1
b11000000111001 <
b11000000111001 I
b11000000111001 Q
b1100111111000110 J
b10101101100111 G
b10101101100111 E
b10101101100111 8
b10101101100111 H
b10101101100111 R
b110 "
b110 2
b110 L
b110 N
0%
#13
1%
#14
0+
13
b1100111111000111 #
b1100111111000111 1
b1100111111000111 <
b1100111111000111 I
b1100111111000111 Q
b1111111111111111 F
b11000000111000 J
b11000000111001 G
1/
b1111101000 :
b1111101000 O
00
b0 D
b11000000111001 E
15
06
17
1C
b111 "
b111 2
b111 L
b111 N
b11000000111001 8
b11000000111001 H
b11000000111001 R
b1111101000 '
b1111101000 -
0%
#15
1%
#16
b1111101000 ;
b1111101000 A
b1111101000 $
b1111101000 *
b1111101000 9
b1111101000 M
b1111101000 P
b1000 "
b1000 2
b1000 L
b1000 N
0%
#17
1+
03
0/
b11000000111001 J
b11000000111001 #
b11000000111001 1
b11000000111001 <
b11000000111001 I
b11000000111001 Q
1!
07
b11000000111001 :
b11000000111001 O
0=
0>
b1110001100001000 '
b1110001100001000 -
1%
#18
b1001 "
b1001 2
b1001 L
b1001 N
0%
#19
1%
#20
0+
13
1/
b1111101001 :
b1111101001 O
b11000000111000 J
b1100111111000111 #
b1100111111000111 1
b1100111111000111 <
b1100111111000111 I
b1100111111000111 Q
0!
17
1=
1>
b1010 "
b1010 2
b1010 L
b1010 N
b1111101001 '
b1111101001 -
0%
#21
1%
#22
b1111101001 ;
b1111101001 A
b1011 "
b1011 2
b1011 L
b1011 N
b1111101001 $
b1111101001 *
b1111101001 9
b1111101001 M
b1111101001 P
0%
#23
1+
03
0/
10
b11000000111000 #
b11000000111000 1
b11000000111000 <
b11000000111000 I
b11000000111000 Q
1!
16
07
b11000000111000 :
b11000000111000 O
0>
b1110001110011000 '
b1110001110011000 -
1%
#24
b11000000110111 :
b11000000110111 O
b11000000110111 #
b11000000110111 1
b11000000110111 <
b11000000110111 I
b11000000110111 Q
b11000000110111 J
b11000000111000 G
b11000000111000 E
b11000000111000 8
b11000000111000 H
b11000000111000 R
b1100 "
b1100 2
b1100 L
b1100 N
0%
#25
1%
#26
0+
b11000000110110 J
13
b11000000110111 G
1/
b1111101000 :
b1111101000 O
00
b1100111111001001 #
b1100111111001001 1
b1100111111001001 <
b1100111111001001 I
b1100111111001001 Q
0!
b11000000110111 E
06
17
1>
b1101 "
b1101 2
b1101 L
b1101 N
b11000000110111 8
b11000000110111 H
b11000000110111 R
b1111101000 '
b1111101000 -
0%
#27
1%
#28
b1111101000 ;
b1111101000 A
b1111101000 $
b1111101000 *
b1111101000 9
b1111101000 M
b1111101000 P
b1110 "
b1110 2
b1110 L
b1110 N
0%
#29
1+
03
b11000000110111 #
b11000000110111 1
b11000000110111 <
b11000000110111 I
b11000000110111 Q
b1100111111001000 J
0/
10
b0 ;
b0 A
b1100111111001000 G
b0 D
b0 F
05
16
07
b11000000110111 :
b11000000110111 O
1?
0C
0@
b1111010011010000 '
b1111010011010000 -
1%
#30
b1111 "
b1111 2
b1111 L
b1111 N
0%
#31
b10011010000 :
b10011010000 O
b10011010000 #
b10011010000 1
b10011010000 <
b10011010000 I
b10011010000 Q
b1111101100101111 J
b10101101100111 F
b10101101100111 D
b10101101100111 ;
b10101101100111 A
b10101101100111 &
b10101101100111 ,
1%
#32
0+
13
b1101100101101001 :
b1101100101101001 O
b1101100101101001 #
b1101100101101001 1
b1101100101101001 <
b1101100101101001 I
b1101100101101001 Q
b10011010010110 J
b1111101100101111 G
b10011010000 E
b10011010000 8
b10011010000 H
b10011010000 R
b10000 "
b10000 2
b10000 L
b10000 N
0%
#33
1%
#34
1+
b1111101000 F
1/
b1111101000 D
03
b1110 :
b1110 O
00
b1111101000 ;
b1111101000 A
b1101100101101001 G
b101101000 J
b101101000 #
b101101000 1
b101101000 <
b101101000 I
b101101000 Q
b1101100101101001 E
15
06
0?
0=
0>
b10001 "
b10001 2
b10001 L
b10001 N
b1101100101101001 8
b1101100101101001 H
b1101100101101001 R
b1110 '
b1110 -
0%
#35
1%
#36
b1000 #
b1000 1
b1000 <
b1000 I
b1000 Q
b1000 J
b1110 F
b1110 D
b1110 ;
b1110 A
b1110 $
b1110 *
b1110 9
b1110 M
b1110 P
b10010 "
b10010 2
b10010 L
b10010 N
0%
#37
1.
0+
13
b1101100101101001 #
b1101100101101001 1
b1101100101101001 <
b1101100101101001 I
b1101100101101001 Q
b1101100101101001 J
0/
b0 D
b1111111111111111 F
05
b1101100101101001 :
b1101100101101001 O
1C
1@
b1110001100000100 '
b1110001100000100 -
1%
#38
b1110 "
b1110 2
b1110 L
b1110 N
0%
#39
1%
#40
1+
03
1/
b1111100111 :
b1111100111 O
b1101100101101000 J
b10011010010111 #
b10011010010111 1
b10011010010111 <
b10011010010111 I
b10011010010111 Q
0.
17
1=
1>
b1111100111 '
b1111100111 -
0%
#41
1%
#42
b1111100111 ;
b1111100111 A
b1111 "
b1111 2
b1111 L
b1111 N
b1111100111 $
b1111100111 *
b1111100111 9
b1111100111 M
b1111100111 P
0%
#43
1+
03
b1111101000 #
b1111101000 1
b1111101000 <
b1111101000 I
b1111101000 Q
b1111110000011000 F
b1111110000010111 J
b0 E
b1111111111111111 G
b1111100111 D
0.
b1111101000 :
b1111101000 O
1B
1?
0C
b1110110111100000 '
b1110110111100000 -
1%
#44
b1111101001 :
b1111101001 O
b1111101001 #
b1111101001 1
b1111101001 <
b1111101001 I
b1111101001 Q
b1111110000010110 J
b1111110000010111 F
b1111101000 D
b1111101000 ;
b1111101000 A
b1111101000 $
b1111101000 *
b1111101000 9
b1111101000 M
b1111101000 P
b10000 "
b10000 2
b10000 L
b10000 N
0%
#45
1%
#46
04
0+
b1111111111111111 F
13
b1101100101101001 :
b1101100101101001 O
1!
0/
b1101100101101001 E
b1101100101101001 G
b0 D
b1101100101101001 J
b1101100101101001 #
b1101100101101001 1
b1101100101101001 <
b1101100101101001 I
b1101100101101001 Q
b1111101001 ;
b1111101001 A
15
07
0B
0?
1C
0=
0>
b10001 "
b10001 2
b10001 L
b10001 N
b1111101001 $
b1111101001 *
b1111101001 9
b1111101001 M
b1111101001 P
b1110001100001000 '
b1110001100001000 -
0%
#47
1%
#48
b10010 "
b10010 2
b10010 L
b10010 N
0%
#49
1+
04
03
b101101001 #
b101101001 1
b101101001 <
b101101001 I
b101101001 Q
b101101001 J
1/
b10101 :
b10101 O
b1111101001 D
b1111101001 F
0!
05
16
0C
0@
b10101 '
b10101 -
1%
#50
b1 #
b1 1
b1 <
b1 I
b1 Q
b1 J
b10101 F
b10101 D
b10101 ;
b10101 A
b10011 "
b10011 2
b10011 L
b10011 N
b10101 $
b10101 *
b10101 9
b10101 M
b10101 P
0%
#51
1%
#52
0+
0/
13
b10011010010110 G
b0 D
b1111111111111111 F
b10011010010101 J
b1101100101101010 #
b1101100101101010 1
b1101100101101010 <
b1101100101101010 I
b1101100101101010 Q
0.
06
b1101100101101010 :
b1101100101101010 O
1?
1C
1@
1=
1>
b10100 "
b10100 2
b10100 L
b10100 N
b1110011111000010 '
b1110011111000010 -
0%
#53
1%
#54
b10101 "
b10101 2
b10101 L
b10101 N
0%
#55
04
1+
1/
03
b10 :
b10 O
b1101100101101001 G
b10101 D
b10101 F
b1 J
b1 #
b1 1
b1 <
b1 I
b1 Q
0?
0C
0@
0=
0>
b10 '
b10 -
1%
#56
0+
14
b0 #
b0 1
b0 <
b0 I
b0 Q
b0 J
b10 F
b10 D
b10 ;
b10 A
b10 $
b10 *
b10 9
b10 M
b10 P
b10110 "
b10110 2
b10110 L
b10110 N
0%
#57
1%
#58
04
13
0/
b1101100101101011 #
b1101100101101011 1
b1101100101101011 <
b1101100101101011 I
b1101100101101011 Q
10
b1101100101101011 J
0.
16
b1101100101101011 :
b1101100101101011 O
1=
b10111 "
b10111 2
b10111 L
b10111 N
b1110000010010000 '
b1110000010010000 -
0%
#59
1%
#60
b1101100101101101 :
b1101100101101101 O
b1101100101101101 #
b1101100101101101 1
b1101100101101101 <
b1101100101101101 I
b1101100101101101 Q
b1101100101101101 J
b1101100101101011 G
b1101100101101011 E
b1101100101101011 8
b1101100101101011 H
b1101100101101011 R
b11000 "
b11000 2
b11000 L
b11000 N
0%
#61
1+
b1101100101101010 J
03
1/
b1111101000 :
b1111101000 O
00
b0 D
b1111111111111111 F
b10011010010101 #
b10011010010101 1
b10011010010101 <
b10011010010101 I
b10011010010101 Q
15
06
17
1C
1@
1>
b1111101000 '
b1111101000 -
1%
#62
b1111101000 ;
b1111101000 A
b11001 "
b11001 2
b11001 L
b11001 N
b1111101000 $
b1111101000 *
b1111101000 9
b1111101000 M
b1111101000 P
0%
#63
1%
#64
0+
b1111111111111111 J
13
0/
10
b0 E
b1111111111111111 G
b0 F
b1111111111111111 #
b1111111111111111 1
b1111111111111111 <
b1111111111111111 I
b1111111111111111 Q
05
16
07
b1111111111111111 :
b1111111111111111 O
1B
1?
0@
0>
b11010 "
b11010 2
b11010 L
b11010 N
b1110111010010000 '
b1110111010010000 -
0%
#65
1%
#66
b11011 "
b11011 2
b11011 L
b11011 N
b1111111111111111 8
b1111111111111111 H
b1111111111111111 R
0%
#67
0.
0+
04
13
b1111111111111111 :
b1111111111111111 O
b1111111111111111 #
b1111111111111111 1
b1111111111111111 <
b1111111111111111 I
b1111111111111111 Q
00
b1111111111111111 E
b1111111111111111 G
b1111111111111111 F
b1111111111111111 J
06
0B
0?
1@
0=
b1110001100000001 '
b1110001100000001 -
1%
#68
b11100 "
b11100 2
b11100 L
b11100 N
0%
#69
1%
#70
b11101 "
b11101 2
b11101 L
b11101 N
b1110001100000010 '
b1110001100000010 -
0%
#71
1%
#72
b11110 "
b11110 2
b11110 L
b11110 N
0%
#73
b1110001100000011 '
b1110001100000011 -
1%
#74
b11111 "
b11111 2
b11111 L
b11111 N
0%
#75
1%
#76
1.
b100000 "
b100000 2
b100000 L
b100000 N
b1110001100000100 '
b1110001100000100 -
0%
#77
1%
#78
b1111101000 "
b1111101000 2
b1111101000 L
b1111101000 N
0%
#79
b1110001100000101 '
b1110001100000101 -
1%
#80
0%
#81
1%
#82
b1110001100000110 '
b1110001100000110 -
0%
#83
1%
#84
0%
#85
b1110001100000111 '
b1110001100000111 -
1%
#86
0%
#87
1%
#88
0+
14
03
b0 :
b0 O
0.
b0 G
b0 #
b0 1
b0 <
b0 I
b0 Q
10
b0 E
b0 F
b0 J
16
1B
0@
1=
b1110101010010000 '
b1110101010010000 -
0%
#89
1%
#90
b1111101001 "
b1111101001 2
b1111101001 L
b1111101001 N
b0 8
b0 H
b0 R
0%
#91
00
b1111111111111111 F
06
0B
1@
0=
b1110001100000001 '
b1110001100000001 -
1%
#92
b1111101010 "
b1111101010 2
b1111101010 L
b1111101010 N
0%
#93
1%
#94
1.
b1111101011 "
b1111101011 2
b1111101011 L
b1111101011 N
b1110001100000010 '
b1110001100000010 -
0%
#95
1%
#96
b1111101000 "
b1111101000 2
b1111101000 L
b1111101000 N
0%
#97
b1110001100000011 '
b1110001100000011 -
1%
#98
0%
#99
1%
#100
0.
b1110001100000100 '
b1110001100000100 -
0%
#101
1%
#102
b1111101001 "
b1111101001 2
b1111101001 L
b1111101001 N
0%
#103
b1110001100000101 '
b1110001100000101 -
1%
#104
b1111101010 "
b1111101010 2
b1111101010 L
b1111101010 N
0%
#105
1%
#106
1.
b1111101011 "
b1111101011 2
b1111101011 L
b1111101011 N
b1110001100000110 '
b1110001100000110 -
0%
#107
1%
#108
b1111101000 "
b1111101000 2
b1111101000 L
b1111101000 N
0%
#109
b1110001100000111 '
b1110001100000111 -
1%
#110
0%
#111
1%
#112
1+
0.
04
03
b1 :
b1 O
10
b1111111111111111 G
b1111111111111110 J
b1 #
b1 1
b1 <
b1 I
b1 Q
16
1B
1?
1=
1>
b1110111111010000 '
b1110111111010000 -
0%
#113
1%
#114
b1111101001 "
b1111101001 2
b1111101001 L
b1111101001 N
b1 8
b1 H
b1 R
0%
#115
04
1+
1.
03
b1 :
b1 O
00
b1 E
b1 G
b1 J
b1 #
b1 1
b1 <
b1 I
b1 Q
06
0B
0?
0=
0>
b1110001100000001 '
b1110001100000001 -
1%
#116
b1111101000 "
b1111101000 2
b1111101000 L
b1111101000 N
0%
#117
1%
#118
0.
b1110001100000010 '
b1110001100000010 -
0%
#119
1%
#120
b1111101001 "
b1111101001 2
b1111101001 L
b1111101001 N
0%
#121
1.
b1110001100000011 '
b1110001100000011 -
1%
#122
b1111101000 "
b1111101000 2
b1111101000 L
b1111101000 N
0%
#123
1%
#124
0.
b1110001100000100 '
b1110001100000100 -
0%
#125
1%
#126
b1111101001 "
b1111101001 2
b1111101001 L
b1111101001 N
0%
#127
1.
b1110001100000101 '
b1110001100000101 -
1%
#128
b1111101000 "
b1111101000 2
b1111101000 L
b1111101000 N
0%
#129
1%
#130
0.
b1110001100000110 '
b1110001100000110 -
0%
#131
1%
#132
b1111101001 "
b1111101001 2
b1111101001 L
b1111101001 N
0%
#133
1.
b1110001100000111 '
b1110001100000111 -
1%
#134
b1111101000 "
b1111101000 2
b1111101000 L
b1111101000 N
0%
#135
1%
#136
1(
0%
#137
1%
#138
b0 "
b0 2
b0 L
b0 N
0%
#139
1+
03
1/
b111111111111111 :
b111111111111111 O
b10101101100111 ;
b10101101100111 A
b0 E
b1111111111111111 G
b1111111111111110 J
b1 #
b1 1
b1 <
b1 I
b1 Q
0.
15
16
17
1B
1?
1=
1>
b111111111111111 '
b111111111111111 -
1%
#140
b111111111111111 $
b111111111111111 *
b111111111111111 9
b111111111111111 M
b111111111111111 P
0%
#141
0(
1%
#142
b1 "
b1 2
b1 L
b1 N
0%
